fetch-info/__init__.py
fetch-info/fetch_header.py
fetchhtmlinfo/__init__.py
fetchhtmlinfo/fetch_header.py
fetchhtmlinfo-0.0.6.dist-info/LICENSE.txt
fetchhtmlinfo-0.0.6.dist-info/METADATA
fetchhtmlinfo-0.0.6.dist-info/WHEEL
fetchhtmlinfo-0.0.6.dist-info/top_level.txt
fetchhtmlinfo-0.0.6.dist-info/RECORD
