Metadata-Version: 2.1
Name: fetchhtmlinfo
Version: 0.0.6
Summary: Fetch a header info from header tag in HTML file.
Home-page: https://github.com/laprn/fetch_title.git
Author: laprn
Author-email: y.mrt@tuta.io
License: MIT
Keywords: title
Platform: UNKNOWN
Classifier: Programming Language :: Python :: 3.5
Classifier: Programming Language :: Python :: 3.6
Classifier: Programming Language :: Python :: 3.7
License-File: LICENSE.txt
Requires-Dist: beautifulsoup4
Requires-Dist: charset-normalizer
Requires-Dist: lxml
Requires-Dist: requests
Requires-Dist: urllib3
